ascii_video/__init__.py
ascii_video/cli.py
ascii_video/player.py
ascii_video/video_engine.py
ascii_video/render_strategy/__init__.py
ascii_video/render_strategy/ascii_bw_strategy.py
ascii_video/render_strategy/ascii_color_filled_strategy.py
ascii_video/render_strategy/ascii_color_strategy.py
ascii_video/render_strategy/ascii_strategy.py
ascii_video/render_strategy/image_processor.py
ascii_video/render_strategy/render_strategy.py
ascii_video/strategies/__init__.py
ascii_video/strategies/ascii_bw_strategy.py
ascii_video/strategies/ascii_color_filled_strategy.py
ascii_video/strategies/ascii_color_strategy.py
ascii_video/strategies/ascii_strategies.py
ascii_video/strategies/image_processing.py
ascii_video/strategies/render_strategies.py
ascii_video-1.0.4.dist-info/LICENSE
ascii_video-1.0.4.dist-info/METADATA
ascii_video-1.0.4.dist-info/WHEEL
ascii_video-1.0.4.dist-info/entry_points.txt
ascii_video-1.0.4.dist-info/top_level.txt
ascii_video-1.0.4.dist-info/RECORD
