Metadata-Version: 2.1
Name: ascii-video
Version: 1.0.4
Summary: Convert your videos to ASCII output
Home-page: https://github.com/tukdoan/ascii-video
Author: Kevin Doan
Author-email: k.doan@utexas.edu
License: MIT
Project-URL: Source, https://github.com/tukdoan/ascii-video
Project-URL: Tracker, https://github.com/tukdoan/ascii-video/issues
Keywords: video ascii terminal opencv
Platform: UNKNOWN
Classifier: Programming Language :: Python :: 3
Classifier: Intended Audience :: Developers
Classifier: License :: OSI Approved :: MIT License
Classifier: Operating System :: OS Independent
Requires-Dist: xtermcolor
Requires-Dist: ffmpeg-python
